{
  "classification": "teaching-diagram",
  "arabic_text": "حمد\nشکر\nمدح",
  "urdu_text": "",
  "english_text": "Unconditional\nGenuine\nGRATITUDE\nPRAISE",
  "suggested_citation": null,
  "alt_text": "Teaching diagram on the Arabic root ḥ-m-d: central box 'حمد' branches downward to 'شکر / GRATITUDE' (labelled 'Unconditional') on the left and 'مدح / PRAISE' (labelled 'Genuine') on the right.",
  "confidence": 0.97,
  "notes": "Pedagogical: hamd combines unconditional gratitude (shukr) and genuine praise (madh)."
}
